{
    "Emoji": {
        "type": "emoji",
        "container": [
            {
                "icon": "😂",
                "text": ""
            },
            {
                "icon": "😀",
                "text": ""
            },
            {
                "icon": "😅",
                "text": ""
            },
            {
                "icon": "😊",
                "text": ""
            },
            {
                "icon": "🙂",
                "text": ""
            },
            {
                "icon": "🙃",
                "text": ""
            },
            {
                "icon": "😌",
                "text": ""
            },
            {
                "icon": "😍",
                "text": ""
            },
            {
                "icon": "😘 ",
                "text": ""
            },
            {
                "icon": "😜",
                "text": ""
            },
            {
                "icon": "😝",
                "text": ""
            },
            {
                "icon": "😏",
                "text": ""
            },
            {
                "icon": "😒",
                "text": ""
            },
            {
                "icon": "🙄",
                "text": ""
            },
            {
                "icon": "😳 ",
                "text": ""
            },
            {
                "icon": "😡",
                "text": ""
            },
            {
                "icon": "😔",
                "text": ""
            },
            {
                "icon": "😫",
                "text": ""
            },
            {
                "icon": "😱",
                "text": ""
            },
            {
                "icon": "😭",
                "text": ""
            },
            {
                "icon": "💩",
                "text": ""
            },
            {
                "icon": "👻",
                "text": ""
            },
            {
                "icon": "🙌",
                "text": ""
            },
            {
                "icon": "🖕",
                "text": ""
            },
            {
                "icon": "👍",
                "text": ""
            },
            {
                "icon": "👫",
                "text": ""
            },
            {
                "icon": "👬",
                "text": ""
            },
            {
                "icon": "👭",
                "text": ""
            },
            {
                "icon": "🌚",
                "text": ""
            },
            {
                "icon": "🌝",
                "text": ""
            },
            {
                "icon": "🙈",
                "text": ""
            },
            {
                "icon": "💊",
                "text": ""
            },
            {
                "icon": "😶",
                "text": ""
            },
            {
                "icon": "🙏",
                "text": ""
            },
            {
                "icon": "🍦",
                "text": ""
            },
            {
                "icon": "🍉",
                "text": ""
            },
            {
                "icon": "😣",
                "text": ""
            }
        ]
    },
    "QQ": {
        "type": "image",
        "container": [
            {"icon":"<img src=\"//cdn.jsdelivr.net/gh/zwysun/PicShare@master/OwO/newQQ/aini.gif\" width=32>","text":"aini"},
            {"icon":"<img src=\"//cdn.jsdelivr.net/gh/zwysun/PicShare@master/OwO/newQQ/aixin.gif\" width=32>","text":"aixin"},
            {"icon":"<img src=\"//cdn.jsdelivr.net/gh/zwysun/PicShare@master/OwO/newQQ/aoman.gif\" width=32>","text":"aoman"},
            {"icon":"<img src=\"//cdn.jsdelivr.net/gh/zwysun/PicShare@master/OwO/newQQ/baiyan.gif\" width=32>","text":"baiyan"},
            {"icon":"<img src=\"//cdn.jsdelivr.net/gh/zwysun/PicShare@master/OwO/newQQ/bangbangtang.gif\" width=32>","text":"bangbangtang"},
            {"icon":"<img src=\"//cdn.jsdelivr.net/gh/zwysun/PicShare@master/OwO/newQQ/baojin.gif\" width=32>","text":"baojin"},
            {"icon":"<img src=\"//cdn.jsdelivr.net/gh/zwysun/PicShare@master/OwO/newQQ/baoquan.gif\" width=32>","text":"baoquan"},
            {"icon":"<img src=\"//cdn.jsdelivr.net/gh/zwysun/PicShare@master/OwO/newQQ/bishi.gif\" width=32>","text":"bishi"},
            {"icon":"<img src=\"//cdn.jsdelivr.net/gh/zwysun/PicShare@master/OwO/newQQ/bizui.gif\" width=32>","text":"bizui"},
            {"icon":"<img src=\"//cdn.jsdelivr.net/gh/zwysun/PicShare@master/OwO/newQQ/cahan.gif\" width=32>","text":"cahan"},
            {"icon":"<img src=\"//cdn.jsdelivr.net/gh/zwysun/PicShare@master/OwO/newQQ/caidao.gif\" width=32>","text":"caidao"},
            {"icon":"<img src=\"//cdn.jsdelivr.net/gh/zwysun/PicShare@master/OwO/newQQ/chi.gif\" width=32>","text":"chi"},
            {"icon":"<img src=\"//cdn.jsdelivr.net/gh/zwysun/PicShare@master/OwO/newQQ/ciya.gif\" width=32>","text":"ciya"},
            {"icon":"<img src=\"//cdn.jsdelivr.net/gh/zwysun/PicShare@master/OwO/newQQ/dabing.gif\" width=32>","text":"dabing"},
            {"icon":"<img src=\"//cdn.jsdelivr.net/gh/zwysun/PicShare@master/OwO/newQQ/daku.gif\" width=32>","text":"daku"},
            {"icon":"<img src=\"//cdn.jsdelivr.net/gh/zwysun/PicShare@master/OwO/newQQ/dan.gif\" width=32>","text":"dan"},
            {"icon":"<img src=\"//cdn.jsdelivr.net/gh/zwysun/PicShare@master/OwO/newQQ/deyi.gif\" width=32>","text":"deyi"},
            {"icon":"<img src=\"//cdn.jsdelivr.net/gh/zwysun/PicShare@master/OwO/newQQ/doge.gif\" width=32>","text":"doge"},
            {"icon":"<img src=\"//cdn.jsdelivr.net/gh/zwysun/PicShare@master/OwO/newQQ/fadai.gif\" width=32>","text":"fadai"},
            {"icon":"<img src=\"//cdn.jsdelivr.net/gh/zwysun/PicShare@master/OwO/newQQ/fanu.gif\" width=32>","text":"fanu"},
            {"icon":"<img src=\"//cdn.jsdelivr.net/gh/zwysun/PicShare@master/OwO/newQQ/fendou.gif\" width=32>","text":"fendou"},
            {"icon":"<img src=\"//cdn.jsdelivr.net/gh/zwysun/PicShare@master/OwO/newQQ/ganga.gif\" width=32>","text":"ganga"},
            {"icon":"<img src=\"//cdn.jsdelivr.net/gh/zwysun/PicShare@master/OwO/newQQ/gouyin.gif\" width=32>","text":"gouyin"},
            {"icon":"<img src=\"//cdn.jsdelivr.net/gh/zwysun/PicShare@master/OwO/newQQ/guzhang.gif\" width=32>","text":"guzhang"},
            {"icon":"<img src=\"//cdn.jsdelivr.net/gh/zwysun/PicShare@master/OwO/newQQ/haixiu.gif\" width=32>","text":"haixiu"},
            {"icon":"<img src=\"//cdn.jsdelivr.net/gh/zwysun/PicShare@master/OwO/newQQ/hanxiao.gif\" width=32>","text":"hanxiao"},
            {"icon":"<img src=\"//cdn.jsdelivr.net/gh/zwysun/PicShare@master/OwO/newQQ/haobang.gif\" width=32>","text":"haobang"},
            {"icon":"<img src=\"//cdn.jsdelivr.net/gh/zwysun/PicShare@master/OwO/newQQ/haqian.gif\" width=32>","text":"haqian"},
            {"icon":"<img src=\"//cdn.jsdelivr.net/gh/zwysun/PicShare@master/OwO/newQQ/hecai.gif\" width=32>","text":"hecai"},
            {"icon":"<img src=\"//cdn.jsdelivr.net/gh/zwysun/PicShare@master/OwO/newQQ/hexie.gif\" width=32>","text":"hexie"},
            {"icon":"<img src=\"//cdn.jsdelivr.net/gh/zwysun/PicShare@master/OwO/newQQ/huaixiao.gif\" width=32>","text":"huaixiao"},
            {"icon":"<img src=\"//cdn.jsdelivr.net/gh/zwysun/PicShare@master/OwO/newQQ/jie.gif\" width=32>","text":"jie"},
            {"icon":"<img src=\"//cdn.jsdelivr.net/gh/zwysun/PicShare@master/OwO/newQQ/jingkong.gif\" width=32>","text":"jingkong"},
            {"icon":"<img src=\"//cdn.jsdelivr.net/gh/zwysun/PicShare@master/OwO/newQQ/jingxi.gif\" width=32>","text":"jingxi"},
            {"icon":"<img src=\"//cdn.jsdelivr.net/gh/zwysun/PicShare@master/OwO/newQQ/jingya.gif\" width=32>","text":"jingya"},
            {"icon":"<img src=\"//cdn.jsdelivr.net/gh/zwysun/PicShare@master/OwO/newQQ/juhua.gif\" width=32>","text":"juhua"},
            {"icon":"<img src=\"//cdn.jsdelivr.net/gh/zwysun/PicShare@master/OwO/newQQ/keai.gif\" width=32>","text":"keai"},
            {"icon":"<img src=\"//cdn.jsdelivr.net/gh/zwysun/PicShare@master/OwO/newQQ/kelian.gif\" width=32>","text":"kelian"},
            {"icon":"<img src=\"//cdn.jsdelivr.net/gh/zwysun/PicShare@master/OwO/newQQ/koubi.gif\" width=32>","text":"koubi"},
            {"icon":"<img src=\"//cdn.jsdelivr.net/gh/zwysun/PicShare@master/OwO/newQQ/ku.gif\" width=32>","text":"ku"},
            {"icon":"<img src=\"//cdn.jsdelivr.net/gh/zwysun/PicShare@master/OwO/newQQ/kuaikule.gif\" width=32>","text":"kuaikule"},
            {"icon":"<img src=\"//cdn.jsdelivr.net/gh/zwysun/PicShare@master/OwO/newQQ/kulou.gif\" width=32>","text":"kulou"},
            {"icon":"<img src=\"//cdn.jsdelivr.net/gh/zwysun/PicShare@master/OwO/newQQ/kun.gif\" width=32>","text":"kun"},
            {"icon":"<img src=\"//cdn.jsdelivr.net/gh/zwysun/PicShare@master/OwO/newQQ/lanqiu.gif\" width=32>","text":"lanqiu"},
            {"icon":"<img src=\"//cdn.jsdelivr.net/gh/zwysun/PicShare@master/OwO/newQQ/leiben.gif\" width=32>","text":"leiben"},
            {"icon":"<img src=\"//cdn.jsdelivr.net/gh/zwysun/PicShare@master/OwO/newQQ/lenghan.gif\" width=32>","text":"lenghan"},
            {"icon":"<img src=\"//cdn.jsdelivr.net/gh/zwysun/PicShare@master/OwO/newQQ/liuhan.gif\" width=32>","text":"liuhan"},
            {"icon":"<img src=\"//cdn.jsdelivr.net/gh/zwysun/PicShare@master/OwO/newQQ/liulei.gif\" width=32>","text":"liulei"},
            {"icon":"<img src=\"//cdn.jsdelivr.net/gh/zwysun/PicShare@master/OwO/newQQ/nanguo.gif\" width=32>","text":"nanguo"},
            {"icon":"<img src=\"//cdn.jsdelivr.net/gh/zwysun/PicShare@master/OwO/newQQ/OK.gif\" width=32>","text":"OK"},
            {"icon":"<img src=\"//cdn.jsdelivr.net/gh/zwysun/PicShare@master/OwO/newQQ/penxue.gif\" width=32>","text":"penxue"},
            {"icon":"<img src=\"//cdn.jsdelivr.net/gh/zwysun/PicShare@master/OwO/newQQ/piezui.gif\" width=32>","text":"piezui"},
            {"icon":"<img src=\"//cdn.jsdelivr.net/gh/zwysun/PicShare@master/OwO/newQQ/pijiu.gif\" width=32>","text":"pijiu"},
            {"icon":"<img src=\"//cdn.jsdelivr.net/gh/zwysun/PicShare@master/OwO/newQQ/qiang.gif\" width=32>","text":"qiang"},
            {"icon":"<img src=\"//cdn.jsdelivr.net/gh/zwysun/PicShare@master/OwO/newQQ/qiaoda.gif\" width=32>","text":"qiaoda"},
            {"icon":"<img src=\"//cdn.jsdelivr.net/gh/zwysun/PicShare@master/OwO/newQQ/qinqin.gif\" width=32>","text":"qinqin"},
            {"icon":"<img src=\"//cdn.jsdelivr.net/gh/zwysun/PicShare@master/OwO/newQQ/qiudale.gif\" width=32>","text":"qiudale"},
            {"icon":"<img src=\"//cdn.jsdelivr.net/gh/zwysun/PicShare@master/OwO/newQQ/quantou.gif\" width=32>","text":"quantou"},
            {"icon":"<img src=\"//cdn.jsdelivr.net/gh/zwysun/PicShare@master/OwO/newQQ/saorao.gif\" width=32>","text":"saorao"},
            {"icon":"<img src=\"//cdn.jsdelivr.net/gh/zwysun/PicShare@master/OwO/newQQ/se.gif\" width=32>","text":"se"},
            {"icon":"<img src=\"//cdn.jsdelivr.net/gh/zwysun/PicShare@master/OwO/newQQ/shengli.gif\" width=32>","text":"shengli"},
            {"icon":"<img src=\"//cdn.jsdelivr.net/gh/zwysun/PicShare@master/OwO/newQQ/shouqiang.gif\" width=32>","text":"shouqiang"},
            {"icon":"<img src=\"//cdn.jsdelivr.net/gh/zwysun/PicShare@master/OwO/newQQ/shuai.gif\" width=32>","text":"shuai"},
            {"icon":"<img src=\"//cdn.jsdelivr.net/gh/zwysun/PicShare@master/OwO/newQQ/shui.gif\" width=32>","text":"shui"},
            {"icon":"<img src=\"//cdn.jsdelivr.net/gh/zwysun/PicShare@master/OwO/newQQ/tiaopi.gif\" width=32>","text":"tiaopi"},
            {"icon":"<img src=\"//cdn.jsdelivr.net/gh/zwysun/PicShare@master/OwO/newQQ/touxiao.gif\" width=32>","text":"touxiao"},
            {"icon":"<img src=\"//cdn.jsdelivr.net/gh/zwysun/PicShare@master/OwO/newQQ/tu.gif\" width=32>","text":"tu"},
            {"icon":"<img src=\"//cdn.jsdelivr.net/gh/zwysun/PicShare@master/OwO/newQQ/tuosai.gif\" width=32>","text":"tuosai"},
            {"icon":"<img src=\"//cdn.jsdelivr.net/gh/zwysun/PicShare@master/OwO/newQQ/weiqu.gif\" width=32>","text":"weiqu"},
            {"icon":"<img src=\"//cdn.jsdelivr.net/gh/zwysun/PicShare@master/OwO/newQQ/weixiao.gif\" width=32>","text":"weixiao"},
            {"icon":"<img src=\"//cdn.jsdelivr.net/gh/zwysun/PicShare@master/OwO/newQQ/woshou.gif\" width=32>","text":"woshou"},
            {"icon":"<img src=\"//cdn.jsdelivr.net/gh/zwysun/PicShare@master/OwO/newQQ/wozuimei.gif\" width=32>","text":"wozuimei"},
            {"icon":"<img src=\"//cdn.jsdelivr.net/gh/zwysun/PicShare@master/OwO/newQQ/wunai.gif\" width=32>","text":"wunai"},
            {"icon":"<img src=\"//cdn.jsdelivr.net/gh/zwysun/PicShare@master/OwO/newQQ/xia.gif\" width=32>","text":"xia"},
            {"icon":"<img src=\"//cdn.jsdelivr.net/gh/zwysun/PicShare@master/OwO/newQQ/xiaojiujie.gif\" width=32>","text":"xiaojiujie"},
            {"icon":"<img src=\"//cdn.jsdelivr.net/gh/zwysun/PicShare@master/OwO/newQQ/xiaoku.gif\" width=32>","text":"xiaoku"},
            {"icon":"<img src=\"//cdn.jsdelivr.net/gh/zwysun/PicShare@master/OwO/newQQ/xiaoyanger.gif\" width=32>","text":"xiaoyanger"},
            {"icon":"<img src=\"//cdn.jsdelivr.net/gh/zwysun/PicShare@master/OwO/newQQ/xieyanxiao.gif\" width=32>","text":"xieyanxiao"},
            {"icon":"<img src=\"//cdn.jsdelivr.net/gh/zwysun/PicShare@master/OwO/newQQ/xigua.gif\" width=32>","text":"xigua"},
            {"icon":"<img src=\"//cdn.jsdelivr.net/gh/zwysun/PicShare@master/OwO/newQQ/xu.gif\" width=32>","text":"xu"},
            {"icon":"<img src=\"//cdn.jsdelivr.net/gh/zwysun/PicShare@master/OwO/newQQ/yangtuo.gif\" width=32>","text":"yangtuo"},
            {"icon":"<img src=\"//cdn.jsdelivr.net/gh/zwysun/PicShare@master/OwO/newQQ/yinxian.gif\" width=32>","text":"yinxian"},
            {"icon":"<img src=\"//cdn.jsdelivr.net/gh/zwysun/PicShare@master/OwO/newQQ/yiwen.gif\" width=32>","text":"yiwen"},
            {"icon":"<img src=\"//cdn.jsdelivr.net/gh/zwysun/PicShare@master/OwO/newQQ/youhengheng.gif\" width=32>","text":"youhengheng"},
            {"icon":"<img src=\"//cdn.jsdelivr.net/gh/zwysun/PicShare@master/OwO/newQQ/youling.gif\" width=32>","text":"youling"},
            {"icon":"<img src=\"//cdn.jsdelivr.net/gh/zwysun/PicShare@master/OwO/newQQ/yun.gif\" width=32>","text":"yun"},
            {"icon":"<img src=\"//cdn.jsdelivr.net/gh/zwysun/PicShare@master/OwO/newQQ/zaijian.gif\" width=32>","text":"zaijian"},
            {"icon":"<img src=\"//cdn.jsdelivr.net/gh/zwysun/PicShare@master/OwO/newQQ/zhayanjian.gif\" width=32>","text":"zhayanjian"},
            {"icon":"<img src=\"//cdn.jsdelivr.net/gh/zwysun/PicShare@master/OwO/newQQ/zhemo.gif\" width=32>","text":"zhemo"},
            {"icon":"<img src=\"//cdn.jsdelivr.net/gh/zwysun/PicShare@master/OwO/newQQ/zhouma.gif\" width=32>","text":"zhouma"},
            {"icon":"<img src=\"//cdn.jsdelivr.net/gh/zwysun/PicShare@master/OwO/newQQ/zhuakuang.gif\" width=32>","text":"zhuakuang"},
            {"icon":"<img src=\"//cdn.jsdelivr.net/gh/zwysun/PicShare@master/OwO/newQQ/zuohengheng.gif\" width=32>","text":"zuohengheng"}
        ]
    },
    "Bili": {
        "type": "image",
        "container": [
            {"icon":"<img src=\"//cdn.jsdelivr.net/gh/zwysun/PicShare@master/OwO/Bili/doge.gif\" width=32>","text":"doge"},
            {"icon":"<img src=\"//cdn.jsdelivr.net/gh/zwysun/PicShare@master/OwO/Bili/亲亲.gif\" width=32>","text":"亲亲"},
            {"icon":"<img src=\"//cdn.jsdelivr.net/gh/zwysun/PicShare@master/OwO/Bili/偷笑.gif\" width=32>","text":"偷笑"},
            {"icon":"<img src=\"//cdn.jsdelivr.net/gh/zwysun/PicShare@master/OwO/Bili/再见.gif\" width=32>","text":"再见"},
            {"icon":"<img src=\"//cdn.jsdelivr.net/gh/zwysun/PicShare@master/OwO/Bili/发怒.gif\" width=32>","text":"发怒"},
            {"icon":"<img src=\"//cdn.jsdelivr.net/gh/zwysun/PicShare@master/OwO/Bili/发财.gif\" width=32>","text":"发财"},
            {"icon":"<img src=\"//cdn.jsdelivr.net/gh/zwysun/PicShare@master/OwO/Bili/可爱.gif\" width=32>","text":"可爱"},
            {"icon":"<img src=\"//cdn.jsdelivr.net/gh/zwysun/PicShare@master/OwO/Bili/吐血.gif\" width=32>","text":"吐血"},
            {"icon":"<img src=\"//cdn.jsdelivr.net/gh/zwysun/PicShare@master/OwO/Bili/呆.gif\" width=32>","text":"呆"},
            {"icon":"<img src=\"//cdn.jsdelivr.net/gh/zwysun/PicShare@master/OwO/Bili/呕吐.gif\" width=32>","text":"呕吐"},
            {"icon":"<img src=\"//cdn.jsdelivr.net/gh/zwysun/PicShare@master/OwO/Bili/困.gif\" width=32>","text":"困"},
            {"icon":"<img src=\"//cdn.jsdelivr.net/gh/zwysun/PicShare@master/OwO/Bili/坏笑.gif\" width=32>","text":"坏笑"},
            {"icon":"<img src=\"//cdn.jsdelivr.net/gh/zwysun/PicShare@master/OwO/Bili/大佬.gif\" width=32>","text":"大佬"},
            {"icon":"<img src=\"//cdn.jsdelivr.net/gh/zwysun/PicShare@master/OwO/Bili/大哭.gif\" width=32>","text":"大哭"},
            {"icon":"<img src=\"//cdn.jsdelivr.net/gh/zwysun/PicShare@master/OwO/Bili/委屈.gif\" width=32>","text":"委屈"},
            {"icon":"<img src=\"//cdn.jsdelivr.net/gh/zwysun/PicShare@master/OwO/Bili/害羞.gif\" width=32>","text":"害羞"},
            {"icon":"<img src=\"//cdn.jsdelivr.net/gh/zwysun/PicShare@master/OwO/Bili/尴尬.gif\" width=32>","text":"尴尬"},
            {"icon":"<img src=\"//cdn.jsdelivr.net/gh/zwysun/PicShare@master/OwO/Bili/微笑.gif\" width=32>","text":"微笑"},
            {"icon":"<img src=\"//cdn.jsdelivr.net/gh/zwysun/PicShare@master/OwO/Bili/思考.gif\" width=32>","text":"思考"},
            {"icon":"<img src=\"//cdn.jsdelivr.net/gh/zwysun/PicShare@master/OwO/Bili/惊吓.gif\" width=32>","text":"惊吓"},
            {"icon":"<img src=\"//cdn.jsdelivr.net/gh/zwysun/PicShare@master/OwO/Bili/打脸.gif\" width=32>","text":"打脸"},
            {"icon":"<img src=\"//cdn.jsdelivr.net/gh/zwysun/PicShare@master/OwO/Bili/抓狂.gif\" width=32>","text":"抓狂"},
            {"icon":"<img src=\"//cdn.jsdelivr.net/gh/zwysun/PicShare@master/OwO/Bili/抠鼻子.gif\" width=32>","text":"抠鼻子"},
            {"icon":"<img src=\"//cdn.jsdelivr.net/gh/zwysun/PicShare@master/OwO/Bili/斜眼笑.gif\" width=32>","text":"斜眼笑"},
            {"icon":"<img src=\"//cdn.jsdelivr.net/gh/zwysun/PicShare@master/OwO/Bili/无奈.gif\" width=32>","text":"无奈"},
            {"icon":"<img src=\"//cdn.jsdelivr.net/gh/zwysun/PicShare@master/OwO/Bili/晕.gif\" width=32>","text":"晕"},
            {"icon":"<img src=\"//cdn.jsdelivr.net/gh/zwysun/PicShare@master/OwO/Bili/流汗.gif\" width=32>","text":"流汗"},
            {"icon":"<img src=\"//cdn.jsdelivr.net/gh/zwysun/PicShare@master/OwO/Bili/流鼻血.gif\" width=32>","text":"流鼻血"},
            {"icon":"<img src=\"//cdn.jsdelivr.net/gh/zwysun/PicShare@master/OwO/Bili/点赞.gif\" width=32>","text":"点赞"},
            {"icon":"<img src=\"//cdn.jsdelivr.net/gh/zwysun/PicShare@master/OwO/Bili/生气.gif\" width=32>","text":"生气"},
            {"icon":"<img src=\"//cdn.jsdelivr.net/gh/zwysun/PicShare@master/OwO/Bili/生病.gif\" width=32>","text":"生病"},
            {"icon":"<img src=\"//cdn.jsdelivr.net/gh/zwysun/PicShare@master/OwO/Bili/疑问.gif\" width=32>","text":"疑问"},
            {"icon":"<img src=\"//cdn.jsdelivr.net/gh/zwysun/PicShare@master/OwO/Bili/白眼.gif\" width=32>","text":"白眼"},
            {"icon":"<img src=\"//cdn.jsdelivr.net/gh/zwysun/PicShare@master/OwO/Bili/睡着.gif\" width=32>","text":"睡着"},
            {"icon":"<img src=\"//cdn.jsdelivr.net/gh/zwysun/PicShare@master/OwO/Bili/笑哭.gif\" width=32>","text":"笑哭"},
            {"icon":"<img src=\"//cdn.jsdelivr.net/gh/zwysun/PicShare@master/OwO/Bili/腼腆.gif\" width=32>","text":"腼腆"},
            {"icon":"<img src=\"//cdn.jsdelivr.net/gh/zwysun/PicShare@master/OwO/Bili/色.gif\" width=32>","text":"色"},
            {"icon":"<img src=\"//cdn.jsdelivr.net/gh/zwysun/PicShare@master/OwO/Bili/调皮.gif\" width=32>","text":"调皮"},
            {"icon":"<img src=\"//cdn.jsdelivr.net/gh/zwysun/PicShare@master/OwO/Bili/鄙视.gif\" width=32>","text":"鄙视"},
            {"icon":"<img src=\"//cdn.jsdelivr.net/gh/zwysun/PicShare@master/OwO/Bili/闭嘴.gif\" width=32>","text":"闭嘴"},
            {"icon":"<img src=\"//cdn.jsdelivr.net/gh/zwysun/PicShare@master/OwO/Bili/难过.gif\" width=32>","text":"难过"},
            {"icon":"<img src=\"//cdn.jsdelivr.net/gh/zwysun/PicShare@master/OwO/Bili/馋.gif\" width=32>","text":"馋"},
            {"icon":"<img src=\"//cdn.jsdelivr.net/gh/zwysun/PicShare@master/OwO/Bili/黑人问号.gif\" width=32>","text":"黑人问号"},
            {"icon":"<img src=\"//cdn.jsdelivr.net/gh/zwysun/PicShare@master/OwO/Bili/鼓掌.gif\" width=32>","text":"鼓掌"}
        ]
    },
    "Weibo": {
        "type": "image",
        "container": [
            {"icon":"<img src=\"//cdn.jsdelivr.net/gh/zwysun/PicShare@master/OwO/Weibo/d_1.png\" width=32>","text":"d_1"},
            {"icon":"<img src=\"//cdn.jsdelivr.net/gh/zwysun/PicShare@master/OwO/Weibo/d_22.png\" width=32>","text":"d_22"},
            {"icon":"<img src=\"//cdn.jsdelivr.net/gh/zwysun/PicShare@master/OwO/Weibo/d_23.png\" width=32>","text":"d_23"},
            {"icon":"<img src=\"//cdn.jsdelivr.net/gh/zwysun/PicShare@master/OwO/Weibo/d_24.png\" width=32>","text":"d_24"},
            {"icon":"<img src=\"//cdn.jsdelivr.net/gh/zwysun/PicShare@master/OwO/Weibo/d_25.png\" width=32>","text":"d_25"},
            {"icon":"<img src=\"//cdn.jsdelivr.net/gh/zwysun/PicShare@master/OwO/Weibo/d_26.png\" width=32>","text":"d_26"},
            {"icon":"<img src=\"//cdn.jsdelivr.net/gh/zwysun/PicShare@master/OwO/Weibo/d_27.png\" width=32>","text":"d_27"},
            {"icon":"<img src=\"//cdn.jsdelivr.net/gh/zwysun/PicShare@master/OwO/Weibo/d_28.png\" width=32>","text":"d_28"},
            {"icon":"<img src=\"//cdn.jsdelivr.net/gh/zwysun/PicShare@master/OwO/Weibo/d_29.png\" width=32>","text":"d_29"},
            {"icon":"<img src=\"//cdn.jsdelivr.net/gh/zwysun/PicShare@master/OwO/Weibo/d_30.png\" width=32>","text":"d_30"},
            {"icon":"<img src=\"//cdn.jsdelivr.net/gh/zwysun/PicShare@master/OwO/Weibo/d_31.png\" width=32>","text":"d_31"},
            {"icon":"<img src=\"//cdn.jsdelivr.net/gh/zwysun/PicShare@master/OwO/Weibo/d_32.png\" width=32>","text":"d_32"},
            {"icon":"<img src=\"//cdn.jsdelivr.net/gh/zwysun/PicShare@master/OwO/Weibo/d_33.png\" width=32>","text":"d_33"},
            {"icon":"<img src=\"//cdn.jsdelivr.net/gh/zwysun/PicShare@master/OwO/Weibo/d_4.png\" width=32>","text":"d_4"},
            {"icon":"<img src=\"//cdn.jsdelivr.net/gh/zwysun/PicShare@master/OwO/Weibo/d_5.png\" width=32>","text":"d_5"},
            {"icon":"<img src=\"//cdn.jsdelivr.net/gh/zwysun/PicShare@master/OwO/Weibo/d_6.png\" width=32>","text":"d_6"},
            {"icon":"<img src=\"//cdn.jsdelivr.net/gh/zwysun/PicShare@master/OwO/Weibo/d_7.png\" width=32>","text":"d_7"},
            {"icon":"<img src=\"//cdn.jsdelivr.net/gh/zwysun/PicShare@master/OwO/Weibo/d_8.png\" width=32>","text":"d_8"},
            {"icon":"<img src=\"//cdn.jsdelivr.net/gh/zwysun/PicShare@master/OwO/Weibo/d_9.png\" width=32>","text":"d_9"},
            {"icon":"<img src=\"//cdn.jsdelivr.net/gh/zwysun/PicShare@master/OwO/Weibo/d_aini.png\" width=32>","text":"d_aini"},
            {"icon":"<img src=\"//cdn.jsdelivr.net/gh/zwysun/PicShare@master/OwO/Weibo/d_aoteman.png\" width=32>","text":"d_aoteman"},
            {"icon":"<img src=\"//cdn.jsdelivr.net/gh/zwysun/PicShare@master/OwO/Weibo/d_bingbujiandan.png\" width=32>","text":"d_bingbujiandan"},
            {"icon":"<img src=\"//cdn.jsdelivr.net/gh/zwysun/PicShare@master/OwO/Weibo/d_bishi.png\" width=32>","text":"d_bishi"},
            {"icon":"<img src=\"//cdn.jsdelivr.net/gh/zwysun/PicShare@master/OwO/Weibo/d_dahaqi.png\" width=32>","text":"d_dahaqi"},
            {"icon":"<img src=\"//cdn.jsdelivr.net/gh/zwysun/PicShare@master/OwO/Weibo/d_dalian.png\" width=32>","text":"d_dalian"},
            {"icon":"<img src=\"//cdn.jsdelivr.net/gh/zwysun/PicShare@master/OwO/Weibo/d_ding.png\" width=32>","text":"d_ding"},
            {"icon":"<img src=\"//cdn.jsdelivr.net/gh/zwysun/PicShare@master/OwO/Weibo/d_dlamcj.png\" width=32>","text":"d_dlamcj"},
            {"icon":"<img src=\"//cdn.jsdelivr.net/gh/zwysun/PicShare@master/OwO/Weibo/d_dlamx.png\" width=32>","text":"d_dlamx"},
            {"icon":"<img src=\"//cdn.jsdelivr.net/gh/zwysun/PicShare@master/OwO/Weibo/d_feizao.png\" width=32>","text":"d_feizao"},
            {"icon":"<img src=\"//cdn.jsdelivr.net/gh/zwysun/PicShare@master/OwO/Weibo/d_ganmao.png\" width=32>","text":"d_ganmao"},
            {"icon":"<img src=\"//cdn.jsdelivr.net/gh/zwysun/PicShare@master/OwO/Weibo/d_guile.png\" width=32>","text":"d_guile"},
            {"icon":"<img src=\"//cdn.jsdelivr.net/gh/zwysun/PicShare@master/OwO/Weibo/d_guzhang.png\" width=32>","text":"d_guzhang"},
            {"icon":"<img src=\"//cdn.jsdelivr.net/gh/zwysun/PicShare@master/OwO/Weibo/d_heng.png\" width=32>","text":"d_heng"},
            {"icon":"<img src=\"//cdn.jsdelivr.net/gh/zwysun/PicShare@master/OwO/Weibo/d_huaxin.png\" width=32>","text":"d_huaxin"},
            {"icon":"<img src=\"//cdn.jsdelivr.net/gh/zwysun/PicShare@master/OwO/Weibo/d_keai.png\" width=32>","text":"d_keai"},
            {"icon":"<img src=\"//cdn.jsdelivr.net/gh/zwysun/PicShare@master/OwO/Weibo/d_ku.png\" width=32>","text":"d_ku"},
            {"icon":"<img src=\"//cdn.jsdelivr.net/gh/zwysun/PicShare@master/OwO/Weibo/d_lei.png\" width=32>","text":"d_lei"},
            {"icon":"<img src=\"//cdn.jsdelivr.net/gh/zwysun/PicShare@master/OwO/Weibo/d_qian.png\" width=32>","text":"d_qian"},
            {"icon":"<img src=\"//cdn.jsdelivr.net/gh/zwysun/PicShare@master/OwO/Weibo/d_shenshou.png\" width=32>","text":"d_shenshou"},
            {"icon":"<img src=\"//cdn.jsdelivr.net/gh/zwysun/PicShare@master/OwO/Weibo/d_shiwang.png\" width=32>","text":"d_shiwang"},
            {"icon":"<img src=\"//cdn.jsdelivr.net/gh/zwysun/PicShare@master/OwO/Weibo/d_shuai.png\" width=32>","text":"d_shuai"},
            {"icon":"<img src=\"//cdn.jsdelivr.net/gh/zwysun/PicShare@master/OwO/Weibo/d_sikao.png\" width=32>","text":"d_sikao"},
            {"icon":"<img src=\"//cdn.jsdelivr.net/gh/zwysun/PicShare@master/OwO/Weibo/d_taikaixin.png\" width=32>","text":"d_taikaixin"},
            {"icon":"<img src=\"//cdn.jsdelivr.net/gh/zwysun/PicShare@master/OwO/Weibo/d_tu.png\" width=32>","text":"d_tu"},
            {"icon":"<img src=\"//cdn.jsdelivr.net/gh/zwysun/PicShare@master/OwO/Weibo/d_tuzi.png\" width=32>","text":"d_tuzi"},
            {"icon":"<img src=\"//cdn.jsdelivr.net/gh/zwysun/PicShare@master/OwO/Weibo/d_xiongmao.png\" width=32>","text":"d_xiongmao"},
            {"icon":"<img src=\"//cdn.jsdelivr.net/gh/zwysun/PicShare@master/OwO/Weibo/d_xixi.png\" width=32>","text":"d_xixi"},
            {"icon":"<img src=\"//cdn.jsdelivr.net/gh/zwysun/PicShare@master/OwO/Weibo/d_xu.png\" width=32>","text":"d_xu"},
            {"icon":"<img src=\"//cdn.jsdelivr.net/gh/zwysun/PicShare@master/OwO/Weibo/d_youhengheng.png\" width=32>","text":"d_youhengheng"},
            {"icon":"<img src=\"//cdn.jsdelivr.net/gh/zwysun/PicShare@master/OwO/Weibo/d_yun.png\" width=32>","text":"d_yun"},
            {"icon":"<img src=\"//cdn.jsdelivr.net/gh/zwysun/PicShare@master/OwO/Weibo/d_zhuakuang.png\" width=32>","text":"d_zhuakuang"},
            {"icon":"<img src=\"//cdn.jsdelivr.net/gh/zwysun/PicShare@master/OwO/Weibo/d_zhutou.png\" width=32>","text":"d_zhutou"},
            {"icon":"<img src=\"//cdn.jsdelivr.net/gh/zwysun/PicShare@master/OwO/Weibo/d_zuiyou.png\" width=32>","text":"d_zuiyou"},
            {"icon":"<img src=\"//cdn.jsdelivr.net/gh/zwysun/PicShare@master/OwO/Weibo/d_zuohengheng.png\" width=32>","text":"d_zuohengheng"},
            {"icon":"<img src=\"//cdn.jsdelivr.net/gh/zwysun/PicShare@master/OwO/Weibo/f_geili.png\" width=32>","text":"f_geili"},
            {"icon":"<img src=\"//cdn.jsdelivr.net/gh/zwysun/PicShare@master/OwO/Weibo/f_hufen.png\" width=32>","text":"f_hufen"},
            {"icon":"<img src=\"//cdn.jsdelivr.net/gh/zwysun/PicShare@master/OwO/Weibo/f_jiong.png\" width=32>","text":"f_jiong"},
            {"icon":"<img src=\"//cdn.jsdelivr.net/gh/zwysun/PicShare@master/OwO/Weibo/f_meng.png\" width=32>","text":"f_meng"},
            {"icon":"<img src=\"//cdn.jsdelivr.net/gh/zwysun/PicShare@master/OwO/Weibo/f_shenma.png\" width=32>","text":"f_shenma"},
            {"icon":"<img src=\"//cdn.jsdelivr.net/gh/zwysun/PicShare@master/OwO/Weibo/f_v5.png\" width=32>","text":"f_v5"},
            {"icon":"<img src=\"//cdn.jsdelivr.net/gh/zwysun/PicShare@master/OwO/Weibo/f_xi.png\" width=32>","text":"f_xi"},
            {"icon":"<img src=\"//cdn.jsdelivr.net/gh/zwysun/PicShare@master/OwO/Weibo/f_zhi.png\" width=32>","text":"f_zhi"},
            {"icon":"<img src=\"//cdn.jsdelivr.net/gh/zwysun/PicShare@master/OwO/Weibo/weibo_dog1.png\" width=32>","text":"weibo_dog1"},
            {"icon":"<img src=\"//cdn.jsdelivr.net/gh/zwysun/PicShare@master/OwO/Weibo/weibo_dog11.png\" width=32>","text":"weibo_dog11"},
            {"icon":"<img src=\"//cdn.jsdelivr.net/gh/zwysun/PicShare@master/OwO/Weibo/weibo_dog12.png\" width=32>","text":"weibo_dog12"},
            {"icon":"<img src=\"//cdn.jsdelivr.net/gh/zwysun/PicShare@master/OwO/Weibo/weibo_dog3.png\" width=32>","text":"weibo_dog3"},
            {"icon":"<img src=\"//cdn.jsdelivr.net/gh/zwysun/PicShare@master/OwO/Weibo/weibo_dog4.png\" width=32>","text":"weibo_dog4"},
            {"icon":"<img src=\"//cdn.jsdelivr.net/gh/zwysun/PicShare@master/OwO/Weibo/weibo_dog5.png\" width=32>","text":"weibo_dog5"},
            {"icon":"<img src=\"//cdn.jsdelivr.net/gh/zwysun/PicShare@master/OwO/Weibo/weibo_dog6.png\" width=32>","text":"weibo_dog6"},
            {"icon":"<img src=\"//cdn.jsdelivr.net/gh/zwysun/PicShare@master/OwO/Weibo/weibo_dog7.png\" width=32>","text":"weibo_dog7"}
        ]
    },
    "颜文字": {
        "type": "emoticon",
        "container": [
                {
                    "icon": "OωO",
                    "text": "Author: DIYgod"
                },
                {
                    "icon": "|´・ω・)ノ",
                    "text": "Hi"
                },
                {
                    "icon": "ヾ(≧∇≦*)ゝ",
                    "text": "开心"
                },
                {
                    "icon": "(☆ω☆)",
                    "text": "星星眼"
                },
                {
                    "icon": "（╯‵□′）╯︵┴─┴",
                    "text": "掀桌"
                },
                {
                    "icon": "￣﹃￣",
                    "text": "流口水"
                },
                {
                    "icon": "(/ω＼)",
                    "text": "捂脸"
                },
                {
                    "icon": "∠( ᐛ 」∠)＿",
                    "text": "给跪"
                },
                {
                    "icon": "(๑•̀ㅁ•́ฅ)",
                    "text": "Hi"
                },
                {
                    "icon": "→_→",
                    "text": "斜眼"
                },
                {
                    "icon": "୧(๑•̀⌄•́๑)૭",
                    "text": "加油"
                },
                {
                    "icon": "٩(ˊᗜˋ*)و",
                    "text": "有木有WiFi"
                },
                {
                    "icon": "(ノ°ο°)ノ",
                    "text": "前方高能预警"
                },
                {
                    "icon": "(´இ皿இ｀)",
                    "text": "我从未见过如此厚颜无耻之人"
                },
                {
                    "icon": "⌇●﹏●⌇",
                    "text": "吓死宝宝惹"
                },
                {
                    "icon": "(ฅ´ω`ฅ)",
                    "text": "已阅留爪"
                },
                {
                    "icon": "(╯°A°)╯︵○○○",
                    "text": "去吧大师球"
                },
                {
                    "icon": "φ(￣∇￣o)",
                    "text": "太萌惹"
                },
                {
                    "icon": "ヾ(´･ ･｀｡)ノ\"",
                    "text": "咦咦咦"
                },
                {
                    "icon": "( ง ᵒ̌皿ᵒ̌)ง⁼³₌₃",
                    "text": "气呼呼"
                },
                {
                    "icon": "(ó﹏ò｡)",
                    "text": "我受到了惊吓"
                },
                {
                    "icon": "Σ(っ °Д °;)っ",
                    "text": "什么鬼"
                },
                {
                    "icon": "( ,,´･ω･)ﾉ\"(´っω･｀｡)",
                    "text": "摸摸头"
                },
                {
                    "icon": "╮(╯▽╰)╭ ",
                    "text": "无奈"
                },
                {
                    "icon": "o(*////▽////*)q ",
                    "text": "脸红"
                },
                {
                    "icon": "＞﹏＜",
                    "text": ""
                },
                {
                    "icon": "( ๑´•ω•) \"(ㆆᴗㆆ)",
                    "text": ""
                },
                {
                    "icon": "(｡•ˇ‸ˇ•｡)",
                    "text": ""
                }
        ]
    },
    "Tieba": {
        "type": "image",
        "container": [
            {"icon":"<img src=\"//cdn.jsdelivr.net/gh/zwysun/PicShare@master/OwO/Tieba/tieba_emotion_02.png\" width=32>","text":"tieba_emotion_02"},
            {"icon":"<img src=\"//cdn.jsdelivr.net/gh/zwysun/PicShare@master/OwO/Tieba/tieba_emotion_04.png\" width=32>","text":"tieba_emotion_04"},
            {"icon":"<img src=\"//cdn.jsdelivr.net/gh/zwysun/PicShare@master/OwO/Tieba/tieba_emotion_05.png\" width=32>","text":"tieba_emotion_05"},
            {"icon":"<img src=\"//cdn.jsdelivr.net/gh/zwysun/PicShare@master/OwO/Tieba/tieba_emotion_10.png\" width=32>","text":"tieba_emotion_10"},
            {"icon":"<img src=\"//cdn.jsdelivr.net/gh/zwysun/PicShare@master/OwO/Tieba/tieba_emotion_11.png\" width=32>","text":"tieba_emotion_11"},
            {"icon":"<img src=\"//cdn.jsdelivr.net/gh/zwysun/PicShare@master/OwO/Tieba/tieba_emotion_13.png\" width=32>","text":"tieba_emotion_13"},
            {"icon":"<img src=\"//cdn.jsdelivr.net/gh/zwysun/PicShare@master/OwO/Tieba/tieba_emotion_14.png\" width=32>","text":"tieba_emotion_14"},
            {"icon":"<img src=\"//cdn.jsdelivr.net/gh/zwysun/PicShare@master/OwO/Tieba/tieba_emotion_17.png\" width=32>","text":"tieba_emotion_17"},
            {"icon":"<img src=\"//cdn.jsdelivr.net/gh/zwysun/PicShare@master/OwO/Tieba/tieba_emotion_23.png\" width=32>","text":"tieba_emotion_23"},
            {"icon":"<img src=\"//cdn.jsdelivr.net/gh/zwysun/PicShare@master/OwO/Tieba/tieba_emotion_28.png\" width=32>","text":"tieba_emotion_28"},
            {"icon":"<img src=\"//cdn.jsdelivr.net/gh/zwysun/PicShare@master/OwO/Tieba/tieba_emotion_30.png\" width=32>","text":"tieba_emotion_30"},
            {"icon":"<img src=\"//cdn.jsdelivr.net/gh/zwysun/PicShare@master/OwO/Tieba/tieba_emotion_31.png\" width=32>","text":"tieba_emotion_31"},
            {"icon":"<img src=\"//cdn.jsdelivr.net/gh/zwysun/PicShare@master/OwO/Tieba/tieba_emotion_33.png\" width=32>","text":"tieba_emotion_33"},
            {"icon":"<img src=\"//cdn.jsdelivr.net/gh/zwysun/PicShare@master/OwO/Tieba/tieba_emotion_34.png\" width=32>","text":"tieba_emotion_34"},
            {"icon":"<img src=\"//cdn.jsdelivr.net/gh/zwysun/PicShare@master/OwO/Tieba/tieba_emotion_36.png\" width=32>","text":"tieba_emotion_36"},
            {"icon":"<img src=\"//cdn.jsdelivr.net/gh/zwysun/PicShare@master/OwO/Tieba/tieba_emotion_37.png\" width=32>","text":"tieba_emotion_37"},
            {"icon":"<img src=\"//cdn.jsdelivr.net/gh/zwysun/PicShare@master/OwO/Tieba/tieba_emotion_38.png\" width=32>","text":"tieba_emotion_38"},
            {"icon":"<img src=\"//cdn.jsdelivr.net/gh/zwysun/PicShare@master/OwO/Tieba/tieba_emotion_39.png\" width=32>","text":"tieba_emotion_39"},
            {"icon":"<img src=\"//cdn.jsdelivr.net/gh/zwysun/PicShare@master/OwO/Tieba/tieba_emotion_40.png\" width=32>","text":"tieba_emotion_40"},
            {"icon":"<img src=\"//cdn.jsdelivr.net/gh/zwysun/PicShare@master/OwO/Tieba/tieba_emotion_41.png\" width=32>","text":"tieba_emotion_41"},
            {"icon":"<img src=\"//cdn.jsdelivr.net/gh/zwysun/PicShare@master/OwO/Tieba/tieba_emotion_42.png\" width=32>","text":"tieba_emotion_42"},
            {"icon":"<img src=\"//cdn.jsdelivr.net/gh/zwysun/PicShare@master/OwO/Tieba/tieba_emotion_43.png\" width=32>","text":"tieba_emotion_43"},
            {"icon":"<img src=\"//cdn.jsdelivr.net/gh/zwysun/PicShare@master/OwO/Tieba/tieba_emotion_44.png\" width=32>","text":"tieba_emotion_44"},
            {"icon":"<img src=\"//cdn.jsdelivr.net/gh/zwysun/PicShare@master/OwO/Tieba/tieba_emotion_45.png\" width=32>","text":"tieba_emotion_45"},
            {"icon":"<img src=\"//cdn.jsdelivr.net/gh/zwysun/PicShare@master/OwO/Tieba/tieba_emotion_46.png\" width=32>","text":"tieba_emotion_46"},
            {"icon":"<img src=\"//cdn.jsdelivr.net/gh/zwysun/PicShare@master/OwO/Tieba/tieba_emotion_47.png\" width=32>","text":"tieba_emotion_47"},
            {"icon":"<img src=\"//cdn.jsdelivr.net/gh/zwysun/PicShare@master/OwO/Tieba/tieba_emotion_55.png\" width=32>","text":"tieba_emotion_55"},
            {"icon":"<img src=\"//cdn.jsdelivr.net/gh/zwysun/PicShare@master/OwO/Tieba/tieba_emotion_56.png\" width=32>","text":"tieba_emotion_56"},
            {"icon":"<img src=\"//cdn.jsdelivr.net/gh/zwysun/PicShare@master/OwO/Tieba/tieba_emotion_57.png\" width=32>","text":"tieba_emotion_57"},
            {"icon":"<img src=\"//cdn.jsdelivr.net/gh/zwysun/PicShare@master/OwO/Tieba/tieba_emotion_58.png\" width=32>","text":"tieba_emotion_58"},
            {"icon":"<img src=\"//cdn.jsdelivr.net/gh/zwysun/PicShare@master/OwO/Tieba/tieba_emotion_63.png\" width=32>","text":"tieba_emotion_63"},
            {"icon":"<img src=\"//cdn.jsdelivr.net/gh/zwysun/PicShare@master/OwO/Tieba/tieba_emotion_64.png\" width=32>","text":"tieba_emotion_64"},
            {"icon":"<img src=\"//cdn.jsdelivr.net/gh/zwysun/PicShare@master/OwO/Tieba/tieba_emotion_65.png\" width=32>","text":"tieba_emotion_65"},
            {"icon":"<img src=\"//cdn.jsdelivr.net/gh/zwysun/PicShare@master/OwO/Tieba/tieba_emotion_66.png\" width=32>","text":"tieba_emotion_66"},
            {"icon":"<img src=\"//cdn.jsdelivr.net/gh/zwysun/PicShare@master/OwO/Tieba/tieba_emotion_68.png\" width=32>","text":"tieba_emotion_68"},
            {"icon":"<img src=\"//cdn.jsdelivr.net/gh/zwysun/PicShare@master/OwO/Tieba/tieba_emotion_69.png\" width=32>","text":"tieba_emotion_69"},
            {"icon":"<img src=\"//cdn.jsdelivr.net/gh/zwysun/PicShare@master/OwO/Tieba/tieba_emotion_70.png\" width=32>","text":"tieba_emotion_70"},
            {"icon":"<img src=\"//cdn.jsdelivr.net/gh/zwysun/PicShare@master/OwO/Tieba/tieba_emotion_71.png\" width=32>","text":"tieba_emotion_71"},
            {"icon":"<img src=\"//cdn.jsdelivr.net/gh/zwysun/PicShare@master/OwO/Tieba/tieba_emotion_72.png\" width=32>","text":"tieba_emotion_72"},
            {"icon":"<img src=\"//cdn.jsdelivr.net/gh/zwysun/PicShare@master/OwO/Tieba/tieba_emotion_76.png\" width=32>","text":"tieba_emotion_76"},
            {"icon":"<img src=\"//cdn.jsdelivr.net/gh/zwysun/PicShare@master/OwO/Tieba/tieba_emotion_80.png\" width=32>","text":"tieba_emotion_80"},
            {"icon":"<img src=\"//cdn.jsdelivr.net/gh/zwysun/PicShare@master/OwO/Tieba/tieba_emotion_81.png\" width=32>","text":"tieba_emotion_81"},
            {"icon":"<img src=\"//cdn.jsdelivr.net/gh/zwysun/PicShare@master/OwO/Tieba/tieba_emotion_83.png\" width=32>","text":"tieba_emotion_83"},
            {"icon":"<img src=\"//cdn.jsdelivr.net/gh/zwysun/PicShare@master/OwO/Tieba/tieba_emotion_84.png\" width=32>","text":"tieba_emotion_84"},
            {"icon":"<img src=\"//cdn.jsdelivr.net/gh/zwysun/PicShare@master/OwO/Tieba/tieba_emotion_85.png\" width=32>","text":"tieba_emotion_85"},
            {"icon":"<img src=\"//cdn.jsdelivr.net/gh/zwysun/PicShare@master/OwO/Tieba/tieba_emotion_86.png\" width=32>","text":"tieba_emotion_86"}
        ]
    },
    "CoolApk": {
        "type": "image",
        "container": [
            {"icon":"<img src=\"//cdn.jsdelivr.net/gh/zwysun/PicShare@master/OwO/Coolapk/coolapk_emotion_100_qqdoge.png\" width=32>","text":"coolapk_emotion_100_qqdoge"},
            {"icon":"<img src=\"//cdn.jsdelivr.net/gh/zwysun/PicShare@master/OwO/Coolapk/coolapk_emotion_1010.png\" width=32>","text":"coolapk_emotion_1010"},
            {"icon":"<img src=\"//cdn.jsdelivr.net/gh/zwysun/PicShare@master/OwO/Coolapk/coolapk_emotion_1011.png\" width=32>","text":"coolapk_emotion_1011"},
            {"icon":"<img src=\"//cdn.jsdelivr.net/gh/zwysun/PicShare@master/OwO/Coolapk/coolapk_emotion_1012.png\" width=32>","text":"coolapk_emotion_1012"},
            {"icon":"<img src=\"//cdn.jsdelivr.net/gh/zwysun/PicShare@master/OwO/Coolapk/coolapk_emotion_1013.png\" width=32>","text":"coolapk_emotion_1013"},
            {"icon":"<img src=\"//cdn.jsdelivr.net/gh/zwysun/PicShare@master/OwO/Coolapk/coolapk_emotion_1014.png\" width=32>","text":"coolapk_emotion_1014"},
            {"icon":"<img src=\"//cdn.jsdelivr.net/gh/zwysun/PicShare@master/OwO/Coolapk/coolapk_emotion_1015.png\" width=32>","text":"coolapk_emotion_1015"},
            {"icon":"<img src=\"//cdn.jsdelivr.net/gh/zwysun/PicShare@master/OwO/Coolapk/coolapk_emotion_1016.png\" width=32>","text":"coolapk_emotion_1016"},
            {"icon":"<img src=\"//cdn.jsdelivr.net/gh/zwysun/PicShare@master/OwO/Coolapk/coolapk_emotion_1017.png\" width=32>","text":"coolapk_emotion_1017"},
            {"icon":"<img src=\"//cdn.jsdelivr.net/gh/zwysun/PicShare@master/OwO/Coolapk/coolapk_emotion_1018.png\" width=32>","text":"coolapk_emotion_1018"},
            {"icon":"<img src=\"//cdn.jsdelivr.net/gh/zwysun/PicShare@master/OwO/Coolapk/coolapk_emotion_1019.png\" width=32>","text":"coolapk_emotion_1019"},
            {"icon":"<img src=\"//cdn.jsdelivr.net/gh/zwysun/PicShare@master/OwO/Coolapk/coolapk_emotion_101_pyjiaoyi.png\" width=32>","text":"coolapk_emotion_101_pyjiaoyi"},
            {"icon":"<img src=\"//cdn.jsdelivr.net/gh/zwysun/PicShare@master/OwO/Coolapk/coolapk_emotion_1020.png\" width=32>","text":"coolapk_emotion_1020"},
            {"icon":"<img src=\"//cdn.jsdelivr.net/gh/zwysun/PicShare@master/OwO/Coolapk/coolapk_emotion_1021.png\" width=32>","text":"coolapk_emotion_1021"},
            {"icon":"<img src=\"//cdn.jsdelivr.net/gh/zwysun/PicShare@master/OwO/Coolapk/coolapk_emotion_102_fadai.png\" width=32>","text":"coolapk_emotion_102_fadai"},
            {"icon":"<img src=\"//cdn.jsdelivr.net/gh/zwysun/PicShare@master/OwO/Coolapk/coolapk_emotion_103_nb.png\" width=32>","text":"coolapk_emotion_103_nb"},
            {"icon":"<img src=\"//cdn.jsdelivr.net/gh/zwysun/PicShare@master/OwO/Coolapk/coolapk_emotion_104.png\" width=32>","text":"coolapk_emotion_104"},
            {"icon":"<img src=\"//cdn.jsdelivr.net/gh/zwysun/PicShare@master/OwO/Coolapk/coolapk_emotion_105.png\" width=32>","text":"coolapk_emotion_105"},
            {"icon":"<img src=\"//cdn.jsdelivr.net/gh/zwysun/PicShare@master/OwO/Coolapk/coolapk_emotion_106.png\" width=32>","text":"coolapk_emotion_106"},
            {"icon":"<img src=\"//cdn.jsdelivr.net/gh/zwysun/PicShare@master/OwO/Coolapk/coolapk_emotion_107.png\" width=32>","text":"coolapk_emotion_107"},
            {"icon":"<img src=\"//cdn.jsdelivr.net/gh/zwysun/PicShare@master/OwO/Coolapk/coolapk_emotion_108.png\" width=32>","text":"coolapk_emotion_108"},
            {"icon":"<img src=\"//cdn.jsdelivr.net/gh/zwysun/PicShare@master/OwO/Coolapk/coolapk_emotion_109.png\" width=32>","text":"coolapk_emotion_109"},
            {"icon":"<img src=\"//cdn.jsdelivr.net/gh/zwysun/PicShare@master/OwO/Coolapk/coolapk_emotion_10_aoman.png\" width=32>","text":"coolapk_emotion_10_aoman"},
            {"icon":"<img src=\"//cdn.jsdelivr.net/gh/zwysun/PicShare@master/OwO/Coolapk/coolapk_emotion_11_yiwen.png\" width=32>","text":"coolapk_emotion_11_yiwen"},
            {"icon":"<img src=\"//cdn.jsdelivr.net/gh/zwysun/PicShare@master/OwO/Coolapk/coolapk_emotion_12_wuyu.png\" width=32>","text":"coolapk_emotion_12_wuyu"},
            {"icon":"<img src=\"//cdn.jsdelivr.net/gh/zwysun/PicShare@master/OwO/Coolapk/coolapk_emotion_13_huaixiao.png\" width=32>","text":"coolapk_emotion_13_huaixiao"},
            {"icon":"<img src=\"//cdn.jsdelivr.net/gh/zwysun/PicShare@master/OwO/Coolapk/coolapk_emotion_14_bishi.png\" width=32>","text":"coolapk_emotion_14_bishi"},
            {"icon":"<img src=\"//cdn.jsdelivr.net/gh/zwysun/PicShare@master/OwO/Coolapk/coolapk_emotion_15_fanu.png\" width=32>","text":"coolapk_emotion_15_fanu"},
            {"icon":"<img src=\"//cdn.jsdelivr.net/gh/zwysun/PicShare@master/OwO/Coolapk/coolapk_emotion_16_tuosai.png\" width=32>","text":"coolapk_emotion_16_tuosai"},
            {"icon":"<img src=\"//cdn.jsdelivr.net/gh/zwysun/PicShare@master/OwO/Coolapk/coolapk_emotion_17_tushe.png\" width=32>","text":"coolapk_emotion_17_tushe"},
            {"icon":"<img src=\"//cdn.jsdelivr.net/gh/zwysun/PicShare@master/OwO/Coolapk/coolapk_emotion_18_han.png\" width=32>","text":"coolapk_emotion_18_han"},
            {"icon":"<img src=\"//cdn.jsdelivr.net/gh/zwysun/PicShare@master/OwO/Coolapk/coolapk_emotion_19_koubi.png\" width=32>","text":"coolapk_emotion_19_koubi"},
            {"icon":"<img src=\"//cdn.jsdelivr.net/gh/zwysun/PicShare@master/OwO/Coolapk/coolapk_emotion_1_hahaha.png\" width=32>","text":"coolapk_emotion_1_hahaha"},
            {"icon":"<img src=\"//cdn.jsdelivr.net/gh/zwysun/PicShare@master/OwO/Coolapk/coolapk_emotion_20_qinqin.png\" width=32>","text":"coolapk_emotion_20_qinqin"},
            {"icon":"<img src=\"//cdn.jsdelivr.net/gh/zwysun/PicShare@master/OwO/Coolapk/coolapk_emotion_21_penxue.png\" width=32>","text":"coolapk_emotion_21_penxue"},
            {"icon":"<img src=\"//cdn.jsdelivr.net/gh/zwysun/PicShare@master/OwO/Coolapk/coolapk_emotion_22_xiaoyan.png\" width=32>","text":"coolapk_emotion_22_xiaoyan"},
            {"icon":"<img src=\"//cdn.jsdelivr.net/gh/zwysun/PicShare@master/OwO/Coolapk/coolapk_emotion_23_shui.png\" width=32>","text":"coolapk_emotion_23_shui"},
            {"icon":"<img src=\"//cdn.jsdelivr.net/gh/zwysun/PicShare@master/OwO/Coolapk/coolapk_emotion_24_wuzuixiao.png\" width=32>","text":"coolapk_emotion_24_wuzuixiao"},
            {"icon":"<img src=\"//cdn.jsdelivr.net/gh/zwysun/PicShare@master/OwO/Coolapk/coolapk_emotion_25_zaijian.png\" width=32>","text":"coolapk_emotion_25_zaijian"},
            {"icon":"<img src=\"//cdn.jsdelivr.net/gh/zwysun/PicShare@master/OwO/Coolapk/coolapk_emotion_26_kelian.png\" width=32>","text":"coolapk_emotion_26_kelian"},
            {"icon":"<img src=\"//cdn.jsdelivr.net/gh/zwysun/PicShare@master/OwO/Coolapk/coolapk_emotion_27_qiang.png\" width=32>","text":"coolapk_emotion_27_qiang"},
            {"icon":"<img src=\"//cdn.jsdelivr.net/gh/zwysun/PicShare@master/OwO/Coolapk/coolapk_emotion_28_ruo.png\" width=32>","text":"coolapk_emotion_28_ruo"},
            {"icon":"<img src=\"//cdn.jsdelivr.net/gh/zwysun/PicShare@master/OwO/Coolapk/coolapk_emotion_29_baoquan.png\" width=32>","text":"coolapk_emotion_29_baoquan"},
            {"icon":"<img src=\"//cdn.jsdelivr.net/gh/zwysun/PicShare@master/OwO/Coolapk/coolapk_emotion_2_jingya.png\" width=32>","text":"coolapk_emotion_2_jingya"},
            {"icon":"<img src=\"//cdn.jsdelivr.net/gh/zwysun/PicShare@master/OwO/Coolapk/coolapk_emotion_30_ok.png\" width=32>","text":"coolapk_emotion_30_ok"},
            {"icon":"<img src=\"//cdn.jsdelivr.net/gh/zwysun/PicShare@master/OwO/Coolapk/coolapk_emotion_31_xiaoku.png\" width=32>","text":"coolapk_emotion_31_xiaoku"},
            {"icon":"<img src=\"//cdn.jsdelivr.net/gh/zwysun/PicShare@master/OwO/Coolapk/coolapk_emotion_32_heiha.png\" width=32>","text":"coolapk_emotion_32_heiha"},
            {"icon":"<img src=\"//cdn.jsdelivr.net/gh/zwysun/PicShare@master/OwO/Coolapk/coolapk_emotion_33_wulian.png\" width=32>","text":"coolapk_emotion_33_wulian"},
            {"icon":"<img src=\"//cdn.jsdelivr.net/gh/zwysun/PicShare@master/OwO/Coolapk/coolapk_emotion_34_jizhi.png\" width=32>","text":"coolapk_emotion_34_jizhi"},
            {"icon":"<img src=\"//cdn.jsdelivr.net/gh/zwysun/PicShare@master/OwO/Coolapk/coolapk_emotion_35_ye.png\" width=32>","text":"coolapk_emotion_35_ye"},
            {"icon":"<img src=\"//cdn.jsdelivr.net/gh/zwysun/PicShare@master/OwO/Coolapk/coolapk_emotion_36_ku.png\" width=32>","text":"coolapk_emotion_36_ku"},
            {"icon":"<img src=\"//cdn.jsdelivr.net/gh/zwysun/PicShare@master/OwO/Coolapk/coolapk_emotion_37_doge.png\" width=32>","text":"coolapk_emotion_37_doge"},
            {"icon":"<img src=\"//cdn.jsdelivr.net/gh/zwysun/PicShare@master/OwO/Coolapk/coolapk_emotion_38_wozuimei.png\" width=32>","text":"coolapk_emotion_38_wozuimei"},
            {"icon":"<img src=\"//cdn.jsdelivr.net/gh/zwysun/PicShare@master/OwO/Coolapk/coolapk_emotion_39_caidao.png\" width=32>","text":"coolapk_emotion_39_caidao"},
            {"icon":"<img src=\"//cdn.jsdelivr.net/gh/zwysun/PicShare@master/OwO/Coolapk/coolapk_emotion_3_ciya.png\" width=32>","text":"coolapk_emotion_3_ciya"},
            {"icon":"<img src=\"//cdn.jsdelivr.net/gh/zwysun/PicShare@master/OwO/Coolapk/coolapk_emotion_40_aixin.png\" width=32>","text":"coolapk_emotion_40_aixin"},
            {"icon":"<img src=\"//cdn.jsdelivr.net/gh/zwysun/PicShare@master/OwO/Coolapk/coolapk_emotion_41_meigui.png\" width=32>","text":"coolapk_emotion_41_meigui"},
            {"icon":"<img src=\"//cdn.jsdelivr.net/gh/zwysun/PicShare@master/OwO/Coolapk/coolapk_emotion_42_diaoxie.png\" width=32>","text":"coolapk_emotion_42_diaoxie"},
            {"icon":"<img src=\"//cdn.jsdelivr.net/gh/zwysun/PicShare@master/OwO/Coolapk/coolapk_emotion_43_heixian.png\" width=32>","text":"coolapk_emotion_43_heixian"},
            {"icon":"<img src=\"//cdn.jsdelivr.net/gh/zwysun/PicShare@master/OwO/Coolapk/coolapk_emotion_44_pen.png\" width=32>","text":"coolapk_emotion_44_pen"},
            {"icon":"<img src=\"//cdn.jsdelivr.net/gh/zwysun/PicShare@master/OwO/Coolapk/coolapk_emotion_45_yinxian.png\" width=32>","text":"coolapk_emotion_45_yinxian"},
            {"icon":"<img src=\"//cdn.jsdelivr.net/gh/zwysun/PicShare@master/OwO/Coolapk/coolapk_emotion_46_nanguo.png\" width=32>","text":"coolapk_emotion_46_nanguo"},
            {"icon":"<img src=\"//cdn.jsdelivr.net/gh/zwysun/PicShare@master/OwO/Coolapk/coolapk_emotion_47_weiqu.png\" width=32>","text":"coolapk_emotion_47_weiqu"},
            {"icon":"<img src=\"//cdn.jsdelivr.net/gh/zwysun/PicShare@master/OwO/Coolapk/coolapk_emotion_48_weiweiyixiao.png\" width=32>","text":"coolapk_emotion_48_weiweiyixiao"},
            {"icon":"<img src=\"//cdn.jsdelivr.net/gh/zwysun/PicShare@master/OwO/Coolapk/coolapk_emotion_49_huanhu.png\" width=32>","text":"coolapk_emotion_49_huanhu"},
            {"icon":"<img src=\"//cdn.jsdelivr.net/gh/zwysun/PicShare@master/OwO/Coolapk/coolapk_emotion_4_liulei.png\" width=32>","text":"coolapk_emotion_4_liulei"},
            {"icon":"<img src=\"//cdn.jsdelivr.net/gh/zwysun/PicShare@master/OwO/Coolapk/coolapk_emotion_50_xinsui.png\" width=32>","text":"coolapk_emotion_50_xinsui"},
            {"icon":"<img src=\"//cdn.jsdelivr.net/gh/zwysun/PicShare@master/OwO/Coolapk/coolapk_emotion_51_chigua.png\" width=32>","text":"coolapk_emotion_51_chigua"},
            {"icon":"<img src=\"//cdn.jsdelivr.net/gh/zwysun/PicShare@master/OwO/Coolapk/coolapk_emotion_52_hejiu.png\" width=32>","text":"coolapk_emotion_52_hejiu"},
            {"icon":"<img src=\"//cdn.jsdelivr.net/gh/zwysun/PicShare@master/OwO/Coolapk/coolapk_emotion_53_pu.png\" width=32>","text":"coolapk_emotion_53_pu"},
            {"icon":"<img src=\"//cdn.jsdelivr.net/gh/zwysun/PicShare@master/OwO/Coolapk/coolapk_emotion_54_hongyaowan.png\" width=32>","text":"coolapk_emotion_54_hongyaowan"},
            {"icon":"<img src=\"//cdn.jsdelivr.net/gh/zwysun/PicShare@master/OwO/Coolapk/coolapk_emotion_55_lvyaowan.png\" width=32>","text":"coolapk_emotion_55_lvyaowan"},
            {"icon":"<img src=\"//cdn.jsdelivr.net/gh/zwysun/PicShare@master/OwO/Coolapk/coolapk_emotion_56_dogexiaoku.png\" width=32>","text":"coolapk_emotion_56_dogexiaoku"},
            {"icon":"<img src=\"//cdn.jsdelivr.net/gh/zwysun/PicShare@master/OwO/Coolapk/coolapk_emotion_57_dogehechi.png\" width=32>","text":"coolapk_emotion_57_dogehechi"},
            {"icon":"<img src=\"//cdn.jsdelivr.net/gh/zwysun/PicShare@master/OwO/Coolapk/coolapk_emotion_58_dogeyuanliangta.png\" width=32>","text":"coolapk_emotion_58_dogeyuanliangta"},
            {"icon":"<img src=\"//cdn.jsdelivr.net/gh/zwysun/PicShare@master/OwO/Coolapk/coolapk_emotion_59_erha.png\" width=32>","text":"coolapk_emotion_59_erha"},
            {"icon":"<img src=\"//cdn.jsdelivr.net/gh/zwysun/PicShare@master/OwO/Coolapk/coolapk_emotion_5_keai.png\" width=32>","text":"coolapk_emotion_5_keai"},
            {"icon":"<img src=\"//cdn.jsdelivr.net/gh/zwysun/PicShare@master/OwO/Coolapk/coolapk_emotion_60_kuan.png\" width=32>","text":"coolapk_emotion_60_kuan"},
            {"icon":"<img src=\"//cdn.jsdelivr.net/gh/zwysun/PicShare@master/OwO/Coolapk/coolapk_emotion_61_lvmao.png\" width=32>","text":"coolapk_emotion_61_lvmao"},
            {"icon":"<img src=\"//cdn.jsdelivr.net/gh/zwysun/PicShare@master/OwO/Coolapk/coolapk_emotion_62_huaji.png\" width=32>","text":"coolapk_emotion_62_huaji"},
            {"icon":"<img src=\"//cdn.jsdelivr.net/gh/zwysun/PicShare@master/OwO/Coolapk/coolapk_emotion_63_liuhanhuaji.png\" width=32>","text":"coolapk_emotion_63_liuhanhuaji"},
            {"icon":"<img src=\"//cdn.jsdelivr.net/gh/zwysun/PicShare@master/OwO/Coolapk/coolapk_emotion_64_shounuehuaji.png\" width=32>","text":"coolapk_emotion_64_shounuehuaji"},
            {"icon":"<img src=\"//cdn.jsdelivr.net/gh/zwysun/PicShare@master/OwO/Coolapk/coolapk_emotion_65_coshuaji.png\" width=32>","text":"coolapk_emotion_65_coshuaji"},
            {"icon":"<img src=\"//cdn.jsdelivr.net/gh/zwysun/PicShare@master/OwO/Coolapk/coolapk_emotion_66_doujiyanhuaji.png\" width=32>","text":"coolapk_emotion_66_doujiyanhuaji"},
            {"icon":"<img src=\"//cdn.jsdelivr.net/gh/zwysun/PicShare@master/OwO/Coolapk/coolapk_emotion_67_mojinghuaji.png\" width=32>","text":"coolapk_emotion_67_mojinghuaji"},
            {"icon":"<img src=\"//cdn.jsdelivr.net/gh/zwysun/PicShare@master/OwO/Coolapk/coolapk_emotion_68.png\" width=32>","text":"coolapk_emotion_68"},
            {"icon":"<img src=\"//cdn.jsdelivr.net/gh/zwysun/PicShare@master/OwO/Coolapk/coolapk_emotion_69.png\" width=32>","text":"coolapk_emotion_69"},
            {"icon":"<img src=\"//cdn.jsdelivr.net/gh/zwysun/PicShare@master/OwO/Coolapk/coolapk_emotion_6_weixiao.png\" width=32>","text":"coolapk_emotion_6_weixiao"},
            {"icon":"<img src=\"//cdn.jsdelivr.net/gh/zwysun/PicShare@master/OwO/Coolapk/coolapk_emotion_70.png\" width=32>","text":"coolapk_emotion_70"},
            {"icon":"<img src=\"//cdn.jsdelivr.net/gh/zwysun/PicShare@master/OwO/Coolapk/coolapk_emotion_71.png\" width=32>","text":"coolapk_emotion_71"},
            {"icon":"<img src=\"//cdn.jsdelivr.net/gh/zwysun/PicShare@master/OwO/Coolapk/coolapk_emotion_72.png\" width=32>","text":"coolapk_emotion_72"},
            {"icon":"<img src=\"//cdn.jsdelivr.net/gh/zwysun/PicShare@master/OwO/Coolapk/coolapk_emotion_73.png\" width=32>","text":"coolapk_emotion_73"},
            {"icon":"<img src=\"//cdn.jsdelivr.net/gh/zwysun/PicShare@master/OwO/Coolapk/coolapk_emotion_74.png\" width=32>","text":"coolapk_emotion_74"},
            {"icon":"<img src=\"//cdn.jsdelivr.net/gh/zwysun/PicShare@master/OwO/Coolapk/coolapk_emotion_75.png\" width=32>","text":"coolapk_emotion_75"},
            {"icon":"<img src=\"//cdn.jsdelivr.net/gh/zwysun/PicShare@master/OwO/Coolapk/coolapk_emotion_76.png\" width=32>","text":"coolapk_emotion_76"},
            {"icon":"<img src=\"//cdn.jsdelivr.net/gh/zwysun/PicShare@master/OwO/Coolapk/coolapk_emotion_77.png\" width=32>","text":"coolapk_emotion_77"},
            {"icon":"<img src=\"//cdn.jsdelivr.net/gh/zwysun/PicShare@master/OwO/Coolapk/coolapk_emotion_78.png\" width=32>","text":"coolapk_emotion_78"},
            {"icon":"<img src=\"//cdn.jsdelivr.net/gh/zwysun/PicShare@master/OwO/Coolapk/coolapk_emotion_79.png\" width=32>","text":"coolapk_emotion_79"},
            {"icon":"<img src=\"//cdn.jsdelivr.net/gh/zwysun/PicShare@master/OwO/Coolapk/coolapk_emotion_7_hehe.png\" width=32>","text":"coolapk_emotion_7_hehe"},
            {"icon":"<img src=\"//cdn.jsdelivr.net/gh/zwysun/PicShare@master/OwO/Coolapk/coolapk_emotion_80.png\" width=32>","text":"coolapk_emotion_80"},
            {"icon":"<img src=\"//cdn.jsdelivr.net/gh/zwysun/PicShare@master/OwO/Coolapk/coolapk_emotion_81_naikezui.png\" width=32>","text":"coolapk_emotion_81_naikezui"},
            {"icon":"<img src=\"//cdn.jsdelivr.net/gh/zwysun/PicShare@master/OwO/Coolapk/coolapk_emotion_82_miaomiao.png\" width=32>","text":"coolapk_emotion_82_miaomiao"},
            {"icon":"<img src=\"//cdn.jsdelivr.net/gh/zwysun/PicShare@master/OwO/Coolapk/coolapk_emotion_83_huoba.png\" width=32>","text":"coolapk_emotion_83_huoba"},
            {"icon":"<img src=\"//cdn.jsdelivr.net/gh/zwysun/PicShare@master/OwO/Coolapk/coolapk_emotion_84_baiyan.png\" width=32>","text":"coolapk_emotion_84_baiyan"},
            {"icon":"<img src=\"//cdn.jsdelivr.net/gh/zwysun/PicShare@master/OwO/Coolapk/coolapk_emotion_85.png\" width=32>","text":"coolapk_emotion_85"},
            {"icon":"<img src=\"//cdn.jsdelivr.net/gh/zwysun/PicShare@master/OwO/Coolapk/coolapk_emotion_86.png\" width=32>","text":"coolapk_emotion_86"},
            {"icon":"<img src=\"//cdn.jsdelivr.net/gh/zwysun/PicShare@master/OwO/Coolapk/coolapk_emotion_87.png\" width=32>","text":"coolapk_emotion_87"},
            {"icon":"<img src=\"//cdn.jsdelivr.net/gh/zwysun/PicShare@master/OwO/Coolapk/coolapk_emotion_88.png\" width=32>","text":"coolapk_emotion_88"},
            {"icon":"<img src=\"//cdn.jsdelivr.net/gh/zwysun/PicShare@master/OwO/Coolapk/coolapk_emotion_89.png\" width=32>","text":"coolapk_emotion_89"},
            {"icon":"<img src=\"//cdn.jsdelivr.net/gh/zwysun/PicShare@master/OwO/Coolapk/coolapk_emotion_8_piezui.png\" width=32>","text":"coolapk_emotion_8_piezui"},
            {"icon":"<img src=\"//cdn.jsdelivr.net/gh/zwysun/PicShare@master/OwO/Coolapk/coolapk_emotion_90.png\" width=32>","text":"coolapk_emotion_90"},
            {"icon":"<img src=\"//cdn.jsdelivr.net/gh/zwysun/PicShare@master/OwO/Coolapk/coolapk_emotion_91.png\" width=32>","text":"coolapk_emotion_91"},
            {"icon":"<img src=\"//cdn.jsdelivr.net/gh/zwysun/PicShare@master/OwO/Coolapk/coolapk_emotion_92.png\" width=32>","text":"coolapk_emotion_92"},
            {"icon":"<img src=\"//cdn.jsdelivr.net/gh/zwysun/PicShare@master/OwO/Coolapk/coolapk_emotion_93.png\" width=32>","text":"coolapk_emotion_93"},
            {"icon":"<img src=\"//cdn.jsdelivr.net/gh/zwysun/PicShare@master/OwO/Coolapk/coolapk_emotion_94.png\" width=32>","text":"coolapk_emotion_94"},
            {"icon":"<img src=\"//cdn.jsdelivr.net/gh/zwysun/PicShare@master/OwO/Coolapk/coolapk_emotion_95_erhading.png\" width=32>","text":"coolapk_emotion_95_erhading"},
            {"icon":"<img src=\"//cdn.jsdelivr.net/gh/zwysun/PicShare@master/OwO/Coolapk/coolapk_emotion_96_kuanlvmao.png\" width=32>","text":"coolapk_emotion_96_kuanlvmao"},
            {"icon":"<img src=\"//cdn.jsdelivr.net/gh/zwysun/PicShare@master/OwO/Coolapk/coolapk_emotion_97_haixiu.png\" width=32>","text":"coolapk_emotion_97_haixiu"},
            {"icon":"<img src=\"//cdn.jsdelivr.net/gh/zwysun/PicShare@master/OwO/Coolapk/coolapk_emotion_98_wunai.png\" width=32>","text":"coolapk_emotion_98_wunai"},
            {"icon":"<img src=\"//cdn.jsdelivr.net/gh/zwysun/PicShare@master/OwO/Coolapk/coolapk_emotion_99_zhoumei.png\" width=32>","text":"coolapk_emotion_99_zhoumei"},
            {"icon":"<img src=\"//cdn.jsdelivr.net/gh/zwysun/PicShare@master/OwO/Coolapk/coolapk_emotion_9_se.png\" width=32>","text":"coolapk_emotion_9_se"},
            {"icon":"<img src=\"//cdn.jsdelivr.net/gh/zwysun/PicShare@master/OwO/Coolapk/c_coolb.png\" width=32>","text":"c_coolb"},
            {"icon":"<img src=\"//cdn.jsdelivr.net/gh/zwysun/PicShare@master/OwO/Coolapk/c_fived.png\" width=32>","text":"c_fived"},
            {"icon":"<img src=\"//cdn.jsdelivr.net/gh/zwysun/PicShare@master/OwO/Coolapk/c_fivef.png\" width=32>","text":"c_fivef"},
            {"icon":"<img src=\"//cdn.jsdelivr.net/gh/zwysun/PicShare@master/OwO/Coolapk/c_fivem.png\" width=32>","text":"c_fivem"},
            {"icon":"<img src=\"//cdn.jsdelivr.net/gh/zwysun/PicShare@master/OwO/Coolapk/c_fiveo.png\" width=32>","text":"c_fiveo"},
            {"icon":"<img src=\"//cdn.jsdelivr.net/gh/zwysun/PicShare@master/OwO/Coolapk/c_fivey.png\" width=32>","text":"c_fivey"},
            {"icon":"<img src=\"//cdn.jsdelivr.net/gh/zwysun/PicShare@master/OwO/Coolapk/c_fy.png\" width=32>","text":"c_fy"},
            {"icon":"<img src=\"//cdn.jsdelivr.net/gh/zwysun/PicShare@master/OwO/Coolapk/c_oned.png\" width=32>","text":"c_oned"},
            {"icon":"<img src=\"//cdn.jsdelivr.net/gh/zwysun/PicShare@master/OwO/Coolapk/c_onef.png\" width=32>","text":"c_onef"},
            {"icon":"<img src=\"//cdn.jsdelivr.net/gh/zwysun/PicShare@master/OwO/Coolapk/c_onem.png\" width=32>","text":"c_onem"},
            {"icon":"<img src=\"//cdn.jsdelivr.net/gh/zwysun/PicShare@master/OwO/Coolapk/c_oneo.png\" width=32>","text":"c_oneo"},
            {"icon":"<img src=\"//cdn.jsdelivr.net/gh/zwysun/PicShare@master/OwO/Coolapk/c_oney.png\" width=32>","text":"c_oney"},
            {"icon":"<img src=\"//cdn.jsdelivr.net/gh/zwysun/PicShare@master/OwO/Coolapk/c_oy.png\" width=32>","text":"c_oy"},
            {"icon":"<img src=\"//cdn.jsdelivr.net/gh/zwysun/PicShare@master/OwO/Coolapk/c_teny.png\" width=32>","text":"c_teny"},
            {"icon":"<img src=\"//cdn.jsdelivr.net/gh/zwysun/PicShare@master/OwO/Coolapk/c_twod.png\" width=32>","text":"c_twod"},
            {"icon":"<img src=\"//cdn.jsdelivr.net/gh/zwysun/PicShare@master/OwO/Coolapk/c_twof.png\" width=32>","text":"c_twof"},
            {"icon":"<img src=\"//cdn.jsdelivr.net/gh/zwysun/PicShare@master/OwO/Coolapk/c_twom.png\" width=32>","text":"c_twom"},
            {"icon":"<img src=\"//cdn.jsdelivr.net/gh/zwysun/PicShare@master/OwO/Coolapk/c_twoo.png\" width=32>","text":"c_twoo"},
            {"icon":"<img src=\"//cdn.jsdelivr.net/gh/zwysun/PicShare@master/OwO/Coolapk/c_twoy.png\" width=32>","text":"c_twoy"},
            {"icon":"<img src=\"//cdn.jsdelivr.net/gh/zwysun/PicShare@master/OwO/Coolapk/c_ty.png\" width=32>","text":"c_ty"}
        ]
    },
    "Valine": {
        "type": "image",
        "container": [
            {
                "text": "smile",
                "icon": "<img src=\"//img.t.sinajs.cn/t4/appstyle/expression/ext/normal/e3/2018new_weixioa02_org.png\" width=32>"
            },
            {
                "text": "lovely",
                "icon": "<img src=\"//img.t.sinajs.cn/t4/appstyle/expression/ext/normal/09/2018new_keai_org.png\" width=32>"
            },
            {
                "text": "happy",
                "icon": "<img src=\"//img.t.sinajs.cn/t4/appstyle/expression/ext/normal/1e/2018new_taikaixin_org.png\" width=32>"
            },
            {
                "text": "clap",
                "icon": "<img src=\"//img.t.sinajs.cn/t4/appstyle/expression/ext/normal/6e/2018new_guzhang_thumb.png\" width=32>"
            },
            {
                "text": "whee",
                "icon": "<img src=\"//img.t.sinajs.cn/t4/appstyle/expression/ext/normal/33/2018new_xixi_thumb.png\" width=32>"
            },
            {
                "text": "haha",
                "icon": "<img src=\"//img.t.sinajs.cn/t4/appstyle/expression/ext/normal/8f/2018new_haha_thumb.png\" width=32>"
            },
            {
                "text": "laugh and cry",
                "icon": "<img src=\"//img.t.sinajs.cn/t4/appstyle/expression/ext/normal/4a/2018new_xiaoku_thumb.png\" width=32>"
            },
            {
                "text": "wink",
                "icon": "<img src=\"//img.t.sinajs.cn/t4/appstyle/expression/ext/normal/43/2018new_jiyan_org.png\" width=32>"
            },
            {
                "text": "greddy",
                "icon": "<img src=\"//img.t.sinajs.cn/t4/appstyle/expression/ext/normal/fa/2018new_chanzui_org.png\" width=32>"
            },
            {
                "text": "awkward",
                "icon": "<img src=\"//img.t.sinajs.cn/t4/appstyle/expression/ext/normal/a3/2018new_heixian_thumb.png\" width=32>"
            },
            {
                "text": "sweat",
                "icon": "<img src=\"//img.t.sinajs.cn/t4/appstyle/expression/ext/normal/28/2018new_han_org.png\" width=32>"
            },
            {
                "text": "pick nose",
                "icon": "<img src=\"//img.t.sinajs.cn/t4/appstyle/expression/ext/normal/9a/2018new_wabi_thumb.png\" width=32>"
            },
            {
                "text": "hum",
                "icon": "<img src=\"//img.t.sinajs.cn/t4/appstyle/expression/ext/normal/7c/2018new_heng_thumb.png\" width=32>"
            },
            {
                "text": "angry",
                "icon": "<img src=\"//img.t.sinajs.cn/t4/appstyle/expression/ext/normal/f6/2018new_nu_thumb.png\" width=32>"
            },
            {
                "text": "grievance",
                "icon": "<img src=\"//img.t.sinajs.cn/t4/appstyle/expression/ext/normal/a5/2018new_weiqu_thumb.png\" width=32>"
            },
            {
                "text": "poor",
                "icon": "<img src=\"//img.t.sinajs.cn/t4/appstyle/expression/ext/normal/96/2018new_kelian_org.png\" width=32>"
            },
            {
                "text": "disappoint",
                "icon": "<img src=\"//img.t.sinajs.cn/t4/appstyle/expression/ext/normal/aa/2018new_shiwang_thumb.png\" width=32>"
            },
            {
                "text": "sad",
                "icon": "<img src=\"//img.t.sinajs.cn/t4/appstyle/expression/ext/normal/ee/2018new_beishang_org.png\" width=32>"
            },
            {
                "text": "tear",
                "icon": "<img src=\"//img.t.sinajs.cn/t4/appstyle/expression/ext/normal/6e/2018new_leimu_org.png\" width=32>"
            },
            {
                "text": "no way",
                "icon": "<img src=\"//img.t.sinajs.cn/t4/appstyle/expression/ext/normal/83/2018new_kuxiao_org.png\" width=32>"
            },
            {
                "text": "shy",
                "icon": "<img src=\"//img.t.sinajs.cn/t4/appstyle/expression/ext/normal/c1/2018new_haixiu_org.png\" width=32>"
            },
            {
                "text": "dirt",
                "icon": "<img src=\"//img.t.sinajs.cn/t4/appstyle/expression/ext/normal/10/2018new_wu_thumb.png\" width=32>"
            },
            {
                "text": "love you",
                "icon": "<img src=\"//img.t.sinajs.cn/t4/appstyle/expression/ext/normal/f6/2018new_aini_org.png\" width=32>"
            },
            {
                "text": "kiss",
                "icon": "<img src=\"//img.t.sinajs.cn/t4/appstyle/expression/ext/normal/2c/2018new_qinqin_thumb.png\" width=32>"
            },
            {
                "text": "amorousness",
                "icon": "<img src=\"//img.t.sinajs.cn/t4/appstyle/expression/ext/normal/9d/2018new_huaxin_org.png\" width=32>"
            },
            {
                "text": "longing",
                "icon": "<img src=\"//img.t.sinajs.cn/t4/appstyle/expression/ext/normal/c9/2018new_chongjing_org.png\" width=32>"
            },
            {
                "text": "desire",
                "icon": "<img src=\"//img.t.sinajs.cn/t4/appstyle/expression/ext/normal/3e/2018new_tianping_thumb.png\" width=32>"
            },
            {
                "text": "bad laugh",
                "icon": "<img src=\"//img.t.sinajs.cn/t4/appstyle/expression/ext/normal/4d/2018new_huaixiao_org.png\" width=32>"
            },
            {
                "text": "blackness",
                "icon": "<img src=\"//img.t.sinajs.cn/t4/appstyle/expression/ext/normal/9e/2018new_yinxian_org.png\" width=32>"
            },
            {
                "text": "laugh without word",
                "icon": "<img src=\"//img.t.sinajs.cn/t4/appstyle/expression/ext/normal/2d/2018new_xiaoerbuyu_org.png\" width=32>"
            },
            {
                "text": "titter",
                "icon": "<img src=\"//img.t.sinajs.cn/t4/appstyle/expression/ext/normal/71/2018new_touxiao_org.png\" width=32>"
            },
            {
                "text": "cool",
                "icon": "<img src=\"//img.t.sinajs.cn/t4/appstyle/expression/ext/normal/c4/2018new_ku_org.png\" width=32>"
            },
            {
                "text": "not easy",
                "icon": "<img src=\"//img.t.sinajs.cn/t4/appstyle/expression/ext/normal/aa/2018new_bingbujiandan_thumb.png\" width=32>"
            },
            {
                "text": "think",
                "icon": "<img src=\"//img.t.sinajs.cn/t4/appstyle/expression/ext/normal/30/2018new_sikao_org.png\" width=32>"
            },
            {
                "text": "question",
                "icon": "<img src=\"//img.t.sinajs.cn/t4/appstyle/expression/ext/normal/b8/2018new_ningwen_org.png\" width=32>"
            },
            {
                "text": "no idea",
                "icon": "<img src=\"//img.t.sinajs.cn/t4/appstyle/expression/ext/normal/2a/2018new_wenhao_thumb.png\" width=32>"
            },
            {
                "text": "dizzy",
                "icon": "<img src=\"//img.t.sinajs.cn/t4/appstyle/expression/ext/normal/07/2018new_yun_thumb.png\" width=32>"
            },
            {
                "text": "bomb",
                "icon": "<img src=\"//img.t.sinajs.cn/t4/appstyle/expression/ext/normal/a2/2018new_shuai_thumb.png\" width=32>"
            },
            {
                "text": "bone",
                "icon": "<img src=\"//img.t.sinajs.cn/t4/appstyle/expression/ext/normal/a1/2018new_kulou_thumb.png\" width=32>"
            },
            {
                "text": "be quiet",
                "icon": "<img src=\"//img.t.sinajs.cn/t4/appstyle/expression/ext/normal/b0/2018new_xu_org.png\" width=32>"
            },
            {
                "text": "shut up",
                "icon": "<img src=\"//img.t.sinajs.cn/t4/appstyle/expression/ext/normal/62/2018new_bizui_org.png\" width=32>"
            },
            {
                "text": "stupid",
                "icon": "<img src=\"//img.t.sinajs.cn/t4/appstyle/expression/ext/normal/dd/2018new_shayan_org.png\" width=32>"
            },
            {
                "text": "surprise ",
                "icon": "<img src=\"//img.t.sinajs.cn/t4/appstyle/expression/ext/normal/49/2018new_chijing_org.png\" width=32>"
            },
            {
                "text": "vomit",
                "icon": "<img src=\"//img.t.sinajs.cn/t4/appstyle/expression/ext/normal/08/2018new_tu_org.png\" width=32>"
            },
            {
                "text": "cold",
                "icon": "<img src=\"//img.t.sinajs.cn/t4/appstyle/expression/ext/normal/40/2018new_kouzhao_thumb.png\" width=32>"
            },
            {
                "text": "sick",
                "icon": "<img src=\"//img.t.sinajs.cn/t4/appstyle/expression/ext/normal/3b/2018new_shengbing_thumb.png\" width=32>"
            },
            {
                "text": "bye",
                "icon": "<img src=\"//img.t.sinajs.cn/t4/appstyle/expression/ext/normal/fd/2018new_baibai_thumb.png\" width=32>"
            },
            {
                "text": "look down on",
                "icon": "<img src=\"//img.t.sinajs.cn/t4/appstyle/expression/ext/normal/da/2018new_bishi_org.png\" width=32>"
            },
            {
                "text": "white eye",
                "icon": "<img src=\"//img.t.sinajs.cn/t4/appstyle/expression/ext/normal/ef/2018new_landelini_org.png\" width=32>"
            },
            {
                "text": "left hum",
                "icon": "<img src=\"//img.t.sinajs.cn/t4/appstyle/expression/ext/normal/43/2018new_zuohengheng_thumb.png\" width=32>"
            },
            {
                "text": "right hum",
                "icon": "<img src=\"//img.t.sinajs.cn/t4/appstyle/expression/ext/normal/c1/2018new_youhengheng_thumb.png\" width=32>"
            },
            {
                "text": "crazy",
                "icon": "<img src=\"//img.t.sinajs.cn/t4/appstyle/expression/ext/normal/17/2018new_zhuakuang_org.png\" width=32>"
            },
            {
                "text": "scold ",
                "icon": "<img src=\"//img.t.sinajs.cn/t4/appstyle/expression/ext/normal/87/2018new_zhouma_thumb.png\" width=32>"
            },
            {
                "text": "hit on face",
                "icon": "<img src=\"//img.t.sinajs.cn/t4/appstyle/expression/ext/normal/cb/2018new_dalian_org.png\" width=32>"
            },
            {
                "text": "wow",
                "icon": "<img src=\"//img.t.sinajs.cn/t4/appstyle/expression/ext/normal/ae/2018new_ding_org.png\" width=32>"
            },
            {
                "text": "fan",
                "icon": "<img src=\"//img.t.sinajs.cn/t4/appstyle/expression/ext/normal/86/2018new_hufen02_org.png\" width=32>"
            },
            {
                "text": "money",
                "icon": "<img src=\"//img.t.sinajs.cn/t4/appstyle/expression/ext/normal/a2/2018new_qian_thumb.png\" width=32>"
            },
            {
                "text": "yawn",
                "icon": "<img src=\"//img.t.sinajs.cn/t4/appstyle/expression/ext/normal/55/2018new_dahaqian_org.png\" width=32>"
            },
            {
                "text": "sleepy",
                "icon": "<img src=\"//img.t.sinajs.cn/t4/appstyle/expression/ext/normal/3c/2018new_kun_thumb.png\" width=32>"
            },
            {
                "text": "sleep",
                "icon": "<img src=\"//img.t.sinajs.cn/t4/appstyle/expression/ext/normal/e2/2018new_shuijiao_thumb.png\" width=32>"
            },
            {
                "text": "watermelon ",
                "icon": "<img src=\"//img.t.sinajs.cn/t4/appstyle/expression/ext/normal/01/2018new_chigua_thumb.png\" width=32>"
            },
            {
                "text": "doge",
                "icon": "<img src=\"//img.t.sinajs.cn/t4/appstyle/expression/ext/normal/a1/2018new_doge02_org.png\" width=32>"
            },
            {
                "text": "dog",
                "icon": "<img src=\"//img.t.sinajs.cn/t4/appstyle/expression/ext/normal/22/2018new_erha_org.png\" width=32>"
            },
            {
                "text": "cat",
                "icon": "<img src=\"//img.t.sinajs.cn/t4/appstyle/expression/ext/normal/7b/2018new_miaomiao_thumb.png\" width=32>"
            },
            {
                "text": "thumb",
                "icon": "<img src=\"//img.t.sinajs.cn/t4/appstyle/expression/ext/normal/e6/2018new_zan_org.png\" width=32>"
            },
            {
                "text": "good",
                "icon": "<img src=\"//img.t.sinajs.cn/t4/appstyle/expression/ext/normal/8a/2018new_good_org.png\" width=32>"
            },
            {
                "text": "ok",
                "icon": "<img src=\"//img.t.sinajs.cn/t4/appstyle/expression/ext/normal/45/2018new_ok_org.png\" width=32>"
            },
            {
                "text": "yeah",
                "icon": "<img src=\"//img.t.sinajs.cn/t4/appstyle/expression/ext/normal/29/2018new_ye_thumb.png\" width=32>"
            },
            {
                "text": "shack hand",
                "icon": "<img src=\"//img.t.sinajs.cn/t4/appstyle/expression/ext/normal/e9/2018new_woshou_thumb.png\" width=32>"
            },
            {
                "text": "bow",
                "icon": "<img src=\"//img.t.sinajs.cn/t4/appstyle/expression/ext/normal/e7/2018new_zuoyi_org.png\" width=32>"
            },
            {
                "text": "come",
                "icon": "<img src=\"//img.t.sinajs.cn/t4/appstyle/expression/ext/normal/42/2018new_guolai_thumb.png\" width=32>"
            },
            {
                "text": "punch",
                "icon": "<img src=\"//img.t.sinajs.cn/t4/appstyle/expression/ext/normal/86/2018new_quantou_thumb.png\" width=32>"
            }
        ]
    }
}